nonebot_plugin_summary/__init__.py
nonebot_plugin_summary/config.py
nonebot_plugin_summary/storage.py
nonebot_plugin_summary/time.py
nonebot_plugin_summary/utils.py
nonebot_plugin_summary-0.4.2.dist-info/LICENSE
nonebot_plugin_summary-0.4.2.dist-info/METADATA
nonebot_plugin_summary-0.4.2.dist-info/WHEEL
nonebot_plugin_summary-0.4.2.dist-info/top_level.txt
nonebot_plugin_summary-0.4.2.dist-info/RECORD
