Metadata-Version: 2.1
Name: nonebot-plugin-summary
Version: 0.4.2
Summary: AI总结群聊消息，再也不用一直爬楼了！
Author-email: ChenXu233 <Woyerpa@outlook.com>
License: MIT
Requires-Python: <=3.13,>=3.9
License-File: LICENSE
Requires-Dist: nonebot2>=2.3.3
Requires-Dist: nonebot-plugin-chatrecorder>=0.6.2
Requires-Dist: nonebot-plugin-send-anything-anywhere>=0.7.1
Requires-Dist: nonebot-plugin-alconna>=0.53.1
Requires-Dist: httpx>=0.27.2
Requires-Dist: nonebot-plugin-userinfo>=0.2.6
Requires-Dist: nonebot-plugin-session-orm>=0.2.0
Requires-Dist: nonebot-plugin-orm>=0.7.6
Requires-Dist: openai>=1.54.3
Requires-Dist: tzlocal>=5.2
Requires-Dist: beautifulsoup4>=4.12.3
